CHANGES.txt
MANIFEST.in
README.txt
bootstrap.py
buildout.cfg
setup.py
docs/LICENSE.GPL
docs/LICENSE.txt
plone/__init__.py
plone.fieldsets.egg-info/PKG-INFO
plone.fieldsets.egg-info/SOURCES.txt
plone.fieldsets.egg-info/dependency_links.txt
plone.fieldsets.egg-info/namespace_packages.txt
plone.fieldsets.egg-info/not-zip-safe
plone.fieldsets.egg-info/requires.txt
plone.fieldsets.egg-info/top_level.txt
plone/fieldsets/__init__.py
plone/fieldsets/fieldsets.py
plone/fieldsets/fieldsets.txt
plone/fieldsets/form.py
plone/fieldsets/interfaces.py
plone/fieldsets/tests.py