Metadata-Version: 1.0
Name: plone.fieldsets
Version: 2.0.2
Summary: An extension to zope.formlib, which allows to group fields into different fieldsets.
Home-page: http://pypi.python.org/pypi/plone.fieldsets
Author: Plone Foundation
Author-email: plone-developers@lists.sourceforge.net
License: GPL version 2
Keywords: zope formlib fieldsets
Platform: UNKNOWN
Classifier: Environment :: Web Environment
Classifier: Framework :: Plone
Classifier: Framework :: Zope2
Classifier: License :: OSI Approved :: GNU General Public License (GPL)
Classifier: Operating System :: OS Independent
Classifier: Programming Language :: Python
